object_store_rs-0.1.0.dist-info/METADATA
object_store_rs-0.1.0.dist-info/WHEEL
object_store_rs.libs/libgcc_s-5b5488a6.so.1
object_store_rs/_list.pyi
object_store_rs/store/_aws.pyi
object_store_rs/store/_gcs.pyi
object_store_rs/store/_client.pyi
object_store_rs/store/_azure.pyi
object_store_rs/store/_http.pyi
object_store_rs/store/_retry.pyi
object_store_rs/store/__init__.pyi
object_store_rs/_rename.pyi
object_store_rs/_sign.pyi
object_store_rs/_get.pyi
object_store_rs/_delete.pyi
object_store_rs/_head.pyi
object_store_rs/_copy.pyi
object_store_rs/__init__.py
object_store_rs/_object_store_rs.pyi
object_store_rs/_put.pyi
object_store_rs/_object_store_rs.abi3.so
object_store_rs-0.1.0.dist-info/RECORD
