Metadata-Version: 2.3
Name: object-store-rs
Version: 0.1.0
Classifier: Programming Language :: Rust
Classifier: Programming Language :: Python :: Implementation :: CPython
Classifier: Programming Language :: Python :: Implementation :: PyPy
Summary: Core library for representing Arrow data in Python.
Keywords: python
Home-Page: https://developmentseed.org/object-store-rs
Author: Kyle Barron <kyle@developmentseed.org>
Author-email: Kyle Barron <kyle@developmentseed.org>
License: MIT OR Apache-2.0
Requires-Python: >=3.9
Project-URL: Source Code, https://github.com/developmentseed/object-store-rs
